tabletalk/__init__.py
tabletalk/app.py
tabletalk/cli.py
tabletalk/factories.py
tabletalk/interfaces.py
tabletalk/main.py
tabletalk/utils.py
tabletalk/providers/__init__.py
tabletalk/providers/anthropic_provider.py
tabletalk/providers/bigquery_provider.py
tabletalk/providers/mysql_provider.py
tabletalk/providers/openai_provider.py
tabletalk/providers/postgres_provider.py
tabletalk/providers/sqlite_provider.py
tabletalk/static/index.html
tabletalk/static/logo.jpg
tabletalk-0.1.99.dist-info/licenses/LICENSE
tabletalk-0.1.99.dist-info/METADATA
tabletalk-0.1.99.dist-info/WHEEL
tabletalk-0.1.99.dist-info/entry_points.txt
tabletalk-0.1.99.dist-info/top_level.txt
tabletalk-0.1.99.dist-info/RECORD
