Metadata-Version: 2.4
Name: tabletalk
Version: 0.1.99
Summary: A command-line tool for managing database schemas and generating SQL queries using natural language.
Home-page: https://github.com/wtbates99/tabletalk
Author: william bates
Author-email: wtbates99@gmail.com
Classifier: Development Status :: 3 - Alpha
Classifier: License :: OSI Approved :: MIT License
Classifier: Programming Language :: Python :: 3.9
Classifier: Programming Language :: Python :: 3.10
Classifier: Programming Language :: Python :: 3.11
Classifier: Programming Language :: Python :: 3.12
Requires-Python: >=3.9
License-File: LICENSE
Requires-Dist: pyyaml>=6.0
Requires-Dist: openai>=1.0.0
Requires-Dist: google-cloud-bigquery>=3.0.0
Requires-Dist: sphinx
Requires-Dist: mysql-connector-python
Requires-Dist: psycopg2-binary
Requires-Dist: anthropic
Requires-Dist: click
Provides-Extra: dev
Requires-Dist: mypy; extra == "dev"
Requires-Dist: types-setuptools; extra == "dev"
Dynamic: author
Dynamic: author-email
Dynamic: classifier
Dynamic: description
Dynamic: description-content-type
Dynamic: home-page
Dynamic: license-file
Dynamic: provides-extra
Dynamic: requires-dist
Dynamic: requires-python
Dynamic: summary
